LICENSE
MANIFEST.in
README.rst
setup.py
ivydepparse/__init__.py
ivydepparse/ivydepparse.py
ivydepparse.egg-info/PKG-INFO
ivydepparse.egg-info/SOURCES.txt
ivydepparse.egg-info/dependency_links.txt
ivydepparse.egg-info/entry_points.txt
ivydepparse.egg-info/requires.txt
ivydepparse.egg-info/top_level.txt
test/test_ivydepparse.py