Metadata-Version: 1.1
Name: ivydepparse
Version: 1.0.0
Summary: Ivy Dependency Parser
Home-page: https://github.com/tt-gf/ivy-dependency-parser
Author: TT-GF Team
Author-email: aurelien.lourot@tomtom.com
License: public domain
Download-URL: https://github.com/tt-gf/ivy-dependency-parser/tarball/1.0.0
Keywords: ivydepparse,ivy,dependency,dependencies,parser,xml,cmake
Platform: UNKNOWN
Classifier: Development Status :: 4 - Beta
Classifier: Environment :: Console
Classifier: Intended Audience :: Developers
Classifier: License :: Public Domain
Classifier: Natural Language :: English
Classifier: Operating System :: POSIX :: Linux
Classifier: Programming Language :: Python :: 2.7
Classifier: Topic :: Software Development :: Build Tools
Classifier: Topic :: System :: Software Distribution
Classifier: Topic :: Text Processing :: Markup :: XML
Classifier: Topic :: Utilities
